5.Memory_driver/memory_driver.v
module memory_driver
    (
        // ----------------------------------------------------------------
        // INPUTS
        input                               clk                 ,
        input                               rst                 , 
        input          [32      -1:0]       concatenated        ,
        // Input to enable writing
        input                               wr_en               ,
        // Input to enable reading
        input                               rd_en               ,   

        // OUTPUTS
        // Output for reading data from memory
        output reg     [32      -1:0]       concatenated_out    ,
        
        // Output to indicate if the memory is empty
        output                              empty               ,
        // Output to indicate if the memory is full
        output                              full                           		  		  
    );

        // ----------------------------------------------------------------
        // REGS
        // Register for tracking the number of words in memory                  
        reg             [4      -1:0]       fifo_counter    = 7'b 0000000 ;
        // Pointer to indicate where the next word should be written
        reg             [6      -1:0]       wr_pointer      = 6'b 000000  ;
        // Pointer - from which cell the next word should be read
        reg             [6      -1:0]       rd_pointer      = 6'b 000000  ;
        // Register for store eight 32 bits words
        reg            [32      -1:0]       fifo_ram    [0:63]            ;
        

        // ----------------------------------------------------------------
        // Assigments 
        assign  empty           =   (fifo_counter   ==   0)               ;
        assign  full            =   (fifo_counter   ==  64)               ;


    // --------------------------------------------------------------------
    // PROCEDURAL BLOCKS        PROCEDURAL BLOCKS        PROCEDURAL BLOCKS
    // --------------------------------------------------------------------


    // --------------------------------------------------------------------
    // WRITE BLOCK
    always  @   (posedge clk)   begin:  write
        // If write is enabled and full is not true
        if      (wr_en == 1  &&  full != 1)
            // save input data in memory at the indicated position
            fifo_ram [wr_pointer]   <=  concatenated                    ;
        // If write is enabled and in the same time read is enabled
        else if (wr_en == 1  &&  rd_en == 1)
            // save input data in memory at the indicated position
            fifo_ram [wr_pointer]   <=  concatenated                    ;
    end 

    // --------------------------------------------------------------------
    // READ BLOCK
    always  @   (posedge clk )   begin:  read
        // If read is enabled and empty is not true
        if      (rd_en == 1  &&  empty != 1)
            // get the output from the indicated position in the memory
            concatenated_out    <=  fifo_ram [rd_pointer]               ;
        // If write is enabled and in the same time read is enabled
        else if (wr_en == 1  &&  rd_en == 1)
            // get the output from the indicated position in the memory
            concatenated_out    <=  fifo_ram [rd_pointer]               ;
    end

    // --------------------------------------------------------------------
    // POINTER BLOCK                    
    always  @   (posedge clk) begin: pointer
        if (rst == 1) begin // If reset is enabled
            wr_pointer  <=  0; // reset write counter (pointer)
            rd_pointer  <=  0; // and reset read counter (pointer)
        end
        else  begin
            // If write is enabled and full is not true
            // or both write and read are enabled
            if ( 
                    (wr_en == 1  &&  full  == 0)  ||  
                    (wr_en == 1  &&  rd_en == 1) 
                ) 
                // increase write counter (pointer)
                wr_pointer  <=  wr_pointer + 1                          ;
            else
                // Otherwise let the counter value remain the same
                wr_pointer  <=  wr_pointer                              ;
            // If read is enabled and empty is not true
            // or both write and read are enabled
            if ( 
                    (rd_en == 1  &&  empty == 0)  ||  
                    (wr_en == 1  &&  rd_en  == 1) 
                ) 
                // increase write counter (pointer)
                rd_pointer  <=  rd_pointer + 1                          ;
            else  
                // Otherwise let the counter value remain the same
                rd_pointer  <=  rd_pointer                              ;
        end
    end

    // --------------------------------------------------------------------
    // COUNTER BLOCK
    always  @   (posedge clk) begin: count
        if (rst == 1)  fifo_counter <= 0; 
        else begin 
            // Concatenate write and read pointer (counter)
            case ({wr_en,rd_en})

                // Case 1: If write is not enabled and read is not enabled
                // the value of memory tarcking counter remain the same
                // (because nothing happens)
                2'b     00  :   fifo_counter    <=    fifo_counter ;    
                  
                // Case 2: If write is not enabled and read is enabled
                                // If there is nothing in memory (empty)
                2'b     01  :   if (fifo_counter  ==  0)
                                // let the counter value remain the zero
                                fifo_counter    <=    0                    ;
                                else
                                // If there is a word(s) in memory
                                // reduce the counter by one                              
                                fifo_counter    <=    fifo_counter  -  1   ;
                            

                // Case 3: If write is enabled and read is not enabled
                                // If counter is equal to eight (is full)                                
                2'b     10  :   if (fifo_counter  ==  8)
                                // let the counter value remain the same
                                fifo_counter    <=    8                    ;
                                else
                                // If memory tracking counter is not full
                                // increase its value by one unit                            
                                fifo_counter    <=    fifo_counter  +  1   ;

                // Case 4: If write is enabled and read is also enabled
                // the value of memory tarcking counter remain the same
                // (because one word enters and at the same time another
                // word leaves the FIFO memory)
                2'b     11  :   fifo_counter    <=    fifo_counter         ;
            endcase
        end                            
    end 

endmodule

5.Memory_driver/button_counter.v
module button_counter
    (
        // ----------------------------------------------------------------
        // Inputs and output
        input                           clk             ,   // Clock
        input                           rst             ,   // Reset  		  
        input                           btn             ,   // Button

        output      [8      -1:0]       button_counter      // Counter 
                                                            // output   
    );


                                
    // --------------------------------------------------------------------
    // Registers
    reg         [2      -1:0]       state                                 ;
    reg         [8      -1:0]       counter_output     =  8'b 00000000    ;

    // --------------------------------------------------------------------
    // Assigment 
    assign  button_counter       =   counter_output                       ;


    // --------------------------------------------------------------------
    // Parameters for different states
    parameter   state_0     =   2'b     00      ;
    parameter   state_1     =   2'b     01      ;
    parameter   state_2     =   2'b     10      ;

      		  
    // --------------------------------------------------------------------
    // Procedural block         Procedural block         Procedural block 
    // --------------------------------------------------------------------

        always  @   (posedge clk)

            if (rst == 1) begin
                state               =   state_0            ;
                counter_output      =         0            ;    
            end
            else
                case (state)

                    state_0:
                        // If the button is pressed
                        if (btn  ==  1) begin
                            // go to state 1 and increase counter by one
                            state           =  state_1              ;
                            counter_output  =  counter_output + 1   ;
                        end else begin 
                            // Otherwise let the state remain the same                           
                            state    =  state_0         ;

                        end                  
                    state_1: begin
                            // On the next positive edge of the clock 
                            // go directly to state 2
                            state    =  state_2         ;
                    end
                    state_2:
                        // If the button is pressed
                        if (btn == 1)  begin
                            // let the state remain the same
                            state    =  state_2         ;
                        end  else  begin
                            // Otherwise go to state 0
                            state    =  state_0         ;
                        end
                endcase


endmodule

5.Memory_driver/testbench.v
`timescale 1ns/100ps

module testbench                                ;
    // -------------------------------------------------------------------
    // Registers and wires
    reg                     clk                 ;   
    reg                     rst                 ; 
    reg                     button              ;

    reg                     wr_en               ;   // Enable writing
    reg                     rd_en               ;   // Enable reading

    wire   [32     -1:0]    concatenated_out    ; 

    wire                    empty               ;   
    wire                    full                ;    


    // -------------------------------------------------------------------
    // Create instance of button_counter_state_machine module
    button_counter    dut_1
    (   
            .clk                (clk)               ,	  
            .rst                (rst)               ,
            .btn                (button)        
    );
	  
    // -------------------------------------------------------------------
    // Create instance of memory_driver module
    memory_driver    dut_2 
    (   
            .wr_en              (wr_en)             ,
            .rd_en              (rd_en)             ,

            .concatenated_out   (concatenated_out)  ,

            .empty              (empty)             ,
            .full               (full)                           
    );

    // -------------------------------------------------------------------
    // Presets
    initial begin
        $dumpvars   ( 1,   testbench )                  ;

        clk             =           1                   ;   
        rst             =           0                   ;     
        wr_en           =           1                   ;   
        rd_en           =           0                   ;
        button          =           0                   ;    

    end

    // -------------------------------------------------------------------
    // Set when to change the clock 
    always  #5 clk = ~clk                               ;


    // -------------------------------------------------------------------
    // TESTS              TESTS              TESTS              TESTS         
    // -------------------------------------------------------------------

    always    @    ( clk or rst or button or wr_en or rd_en) begin

        #15 //At time 15
            button  =   1   ;
                                // Time 20 - first signal to the counter
        #20 //At time 35
            button  =   0   ;


        #10 //At time 45
            button  =   1   ;
                                // Time 50 - second signal to the counter
        #20 //At time 65
            button  =   0   ;


        #10 //At time 75
            button  =   1   ;
                                // Time 80 - third signal to the counter
        #20 //At time 95
            button  =   0   ;


        #10 //At time 105
            button  =   1   ;
                                // Time 110 - fourth signal to the counter
        #20 //At time 125
            button  =   0   ;

            $display();
            $display(concatenated_out);
        
		  
		#100 //At time 
                                                                      
		    $finish;

    end


endmodule

5.Memory_driver/simulation/modelsim/dump.vcd
$date
	Tue Jan 19 18:42:38 2021
$end
$version
	ModelSim Version 10.5b
$end
$timescale
	1ps
$end

$scope module testbench $end
$var reg 1 ! clk $end
$var reg 1 " rst $end
$var reg 1 # button $end
$var reg 1 $ wr_en $end
$var reg 1 % rd_en $end
$var wire 1 & concatenated_out [31] $end
$var wire 1 ' concatenated_out [30] $end
$var wire 1 ( concatenated_out [29] $end
$var wire 1 ) concatenated_out [28] $end
$var wire 1 * concatenated_out [27] $end
$var wire 1 + concatenated_out [26] $end
$var wire 1 , concatenated_out [25] $end
$var wire 1 - concatenated_out [24] $end
$var wire 1 . concatenated_out [23] $end
$var wire 1 / concatenated_out [22] $end
$var wire 1 0 concatenated_out [21] $end
$var wire 1 1 concatenated_out [20] $end
$var wire 1 2 concatenated_out [19] $end
$var wire 1 3 concatenated_out [18] $end
$var wire 1 4 concatenated_out [17] $end
$var wire 1 5 concatenated_out [16] $end
$var wire 1 6 concatenated_out [15] $end
$var wire 1 7 concatenated_out [14] $end
$var wire 1 8 concatenated_out [13] $end
$var wire 1 9 concatenated_out [12] $end
$var wire 1 : concatenated_out [11] $end
$var wire 1 ; concatenated_out [10] $end
$var wire 1 < concatenated_out [9] $end
$var wire 1 = concatenated_out [8] $end
$var wire 1 > concatenated_out [7] $end
$var wire 1 ? concatenated_out [6] $end
$var wire 1 @ concatenated_out [5] $end
$var wire 1 A concatenated_out [4] $end
$var wire 1 B concatenated_out [3] $end
$var wire 1 C concatenated_out [2] $end
$var wire 1 D concatenated_out [1] $end
$var wire 1 E concatenated_out [0] $end
$var wire 1 F empty $end
$var wire 1 G full $end
$upscope $end
$enddefinitions $end
#0
$dumpvars
1!
0"
0#
1$
0%
xE
xD
xC
xB
xA
x@
x?
x>
x=
x<
x;
x:
x9
x8
x7
x6
x5
x4
x3
x2
x1
x0
x/
x.
x-
x,
x+
x*
x)
x(
x'
x&
1F
0G
$end
#5000
0!
#10000
1!
#15000
1#
0!
#20000
1!
#25000
0!
#30000
1!
#35000
0#
0!
#40000
1!
#45000
1#
0!
#50000
1!
#55000
0!
#60000
1!
#65000
0#
0!
#70000
1!
#75000
1#
0!
#80000
1!
#85000
0!
#90000
1!
#95000
0#
0!
#100000
1!
#105000
1#
0!
#110000
1!
#115000
0!
#120000
1!
#125000
0#
0!
