3.Valid_in/valid_in.v
module valid_in_state_machine
    (
        // ----------------------------------------------------------------
        // Inputs and output 
        input                       clk             ,   // Clock
        input                       rst             ,   // Reset  		  
        input                       btn             ,   // Button

        output reg                  out             ,   // Output for
                                                        // the signal 
        output      [2    -1:0]     state_test          // Output for
                                                        // testing the 
                                                        // state register   
    );	 
                                
    // --------------------------------------------------------------------
    // Register and assigment
    reg         [2    -1:0]         state           ;
    assign      state_test    =     state           ;

    // --------------------------------------------------------------------
    // Parameters for different states
    parameter   state_0     =   2'b     00      ;
    parameter   state_1     =   2'b     01      ;
    parameter   state_2     =   2'b     10      ;

      		  
    // --------------------------------------------------------------------
    // Procedural blocks        Procedural blocks        Procedural blocks 
    // --------------------------------------------------------------------

        always  @   (posedge clk)

            if (rst == 1) begin
                // If reset is true, there is no signal
                state           =    state_0            ;
                out             =          0            ;    
            end
            else
                case (state)

                    state_0:
                        // If the button is pressed
                        if (btn  ==  1) begin
                            // go to state 1, in which a signal is given
                            state    =  state_1         ;
                            out      =        1         ;
                        end else begin 
                            // Otherwise let the state remain the same
                            
                            state    =  state_0         ;
                            out      =        0         ;
                        end                  
                    state_1: begin
                            // On the next positive edge of the clock 
                            // go directly to state 2, in which there
                            // is no signal
                            state    =  state_2         ;
                            out      =        0         ;
                    end
                    state_2:
                        // If the button is pressed
                        if (btn == 1)  begin
                            // let the state remain the same
                            // (there is no signal)
                            state    =  state_2         ;
                            out      =        0         ;
                        end  else  begin
                            // Otherwise go to state 0, in which
                            // there is also no signal
                            state    =  state_0         ;
                            out      =        0         ;
                        end
                endcase


endmodule

3.Valid_in/testbench.v
`timescale 1ns/100ps

module testbench                            ;
    // -------------------------------------------------------------------
    // Registers and wire
    reg                     clk             ;   // Clock
    reg                     rst             ;   // Reset
    reg                     btn             ;   // Button
    wire                    out             ;   // Wire for
                                                // the signal
    wire    [2    -1:0]     state_test      ;   // Wire for
                                                // testing the 
                                                // state reg 

    // -------------------------------------------------------------------
    // Create a task to check the values 		  
    task display_the_values                                 ;
	 
        input       [4    -1:0]     statement_number        ; 
	 
        input                       clk_expected            ;
        input                       rst_expected            ;
        input      [16    -1:0]     btn_expected            ;
        input      [16    -1:0]     out_expected            ;
        input       [2    -1:0]     state_test_expected     ;
		  
        input                       clk_actual              ;
        input                       rst_actual              ;
        input      [16    -1:0]     btn_actual              ;
        input      [16    -1:0]     out_actual              ;
        input       [2    -1:0]     state_test_actual       ;
		   
			
            if  (   clk_actual          !=   clk_expected      || 
                    rst_actual          !=   rst_expected      ||
                    btn_actual          !=   btn_expected      || 
                    out_actual          !=   out_expected      ||
                    state_test_actual   !=   state_test_expected  ) begin
						  
                    $display ()                                         ;
                    $display ("STATEMENT  %0d:            Time is:" ,
                               statement_number)					    ;
                    $display ("             ", $time)                   ;
                    $display (" Result: ERROR - the values were wrong!");
                    $display ()                                         ;
                    $display ("   Expected: clk = %0d  reset = %0d" ,
                              clk_expected, rst_expected)               ; 
                    $display ("             btn = %0d  out   = %0d" ,
                              btn_expected, out_expected)               ;
                    $display ("             state_test     = %0d"   ,
                              state_test_expected)                      ;
                    $display ()                                         ;
                    $display ("   Actual:   clk = %0d, reset = %0d" , 
                              clk_actual, rst_actual)                   ;
                    $display ("             btn = %0d, out   = %0d" ,
                              btn_actual, out_actual)                   ;
                    $display ("             state_test     = %0d"   ,
                              state_test_actual)                        ;
                    $display ()                                         ;
						
                    end 
					  
            else    begin
                    $display ()                                         ;
                    $display ("STATEMENT  %0d:            Time is:" ,
                               statement_number)					    ;
                    $display ("             ", $time)                   ;		
                    $display (" Result: The values were correct!")      ;
                    $display ()                                         ;
                    $display ("   Expected: clk = %0d  reset = %0d" ,
                              clk_expected, rst_expected)               ; 
                    $display ("             btn = %0d  out   = %0d" ,
                              btn_expected, out_expected)               ;
                    $display ("             state_test     = %0d" ,
                              state_test_expected)                      ; 
                    $display ()                                         ;
                    $display ("   Actual:   clk = %0d, reset = %0d" , 
                              clk_actual, rst_actual)                   ;
                    $display ("             btn = %0d, out   = %0d" ,
                              btn_actual, out_actual)                   ;
                    $display ("             state_test     = %0d" ,
                              state_test_actual)                        ;
                    $display ()                                         ;
						
                    end
				  
    endtask

    // -------------------------------------------------------------------
    // Create instance of valid_in_state_machine module
    valid_in_state_machine    dut 
    (   
            .clk            (clk)  		  	,	  
            .rst            (rst)           ,
            .btn            (btn)           ,
            .out            (out)           ,
            .state_test     (state_test)    
    );

    // -------------------------------------------------------------------
    // Presets
    initial begin
        $dumpvars   ( 1,   testbench )      ;

        clk         = 1                     ;   
        rst         = 1                     ;   
        btn         = 1                     ;   
        
    end

    // -------------------------------------------------------------------
    // Set when to change the clock 
    always #50 clk = ~clk                   ;


    // -------------------------------------------------------------------
    // TESTS              TESTS              TESTS              TESTS         
    // -------------------------------------------------------------------

    always    @    ( btn or rst or clk ) begin

        // ---------------------------------------------------------------
        #101 // At time 101 - right after  !!! posedge clk !!!                
        // Check that the actual values correspond to the expected ones!
        // The values entered below represent as follows: statement_number, 
        // clk_expected, reset_expected, button_expected, out_expected,
        // state_test_expected, clk_actual, reset_actual, button_actual,
        // out_actual, state_test_actual
        begin
            // Expected values: clk = 1,    rst = 1,    btn = 1, 
            //                  out = 0,    state_test = 0
            display_the_values( 1, 1, 1, 1, 0, 0, clk, rst, btn, 
                                out, state_test )                   ;
        end      

        // ---------------------------------------------------------------
        #50 // At time 151
        // Reset is false
        rst     =      0       ;

        // ---------------------------------------------------------------
        #50 // At time 201 - right after !!! posedge clk !!! 
        // The code execution is entered in the first case of the always
        // block (state_0) where when the button is pressed, the following
        // assignment is set - state <= state_1.

        // Display the values to check them
        begin
            // Expected values: clk = 1,    rst = 0,    btn = 1, 
            //                  out = 1,    state_test = 1 
            display_the_values( 2, 1, 0, 1, 1, 1, clk, rst, btn, 
                                out, state_test )                   ;
        end    

        // ---------------------------------------------------------------
        #100 // At time 301 - right after  !!! posedge clk !!!         
        begin
            // Check if on the next positive edge of the clock, the state 
            // changes directly to state 2, in which there is no signal
            // Expected values: clk = 1,    rst = 0,    btn = 1, 
            //                  out = 0,    state_test = 2
            display_the_values( 3, 1, 0, 1, 0, 2, clk, rst, btn, 
                                out, state_test )                   ;
        end     

        // ---------------------------------------------------------------
        #100 // At time 401 - right after  !!! posedge clk !!!         
        begin
            // Check that the state is still the same
            // while the button is pressed
            // Expected values: clk = 1,    rst = 0,    btn = 1, 
            //                  out = 0,    state_test = 2 
            display_the_values( 4, 1, 0, 1, 0, 2, clk, rst, btn, 
                                out, state_test )                   ;
        end 

        // ---------------------------------------------------------------
        #50 // At time 451
        // Button is false
        btn     =      0       ;

        // ---------------------------------------------------------------
        #50 // At time 501 - right after  !!! posedge clk !!!         
        begin
            // Check whether the state is returned to state 0,
            // when the button is no longer active 
            // Expected values: clk = 1,    rst = 0,    btn = 0, 
            //                  out = 0,    state_test = 0 
            display_the_values( 5, 1, 0, 0, 0, 0, clk, rst, btn, 
                                out, state_test )                   ;
        end

        // ---------------------------------------------------------------
        #50 // At time 551
        // Button is true
        btn     =      1       ;

        // ---------------------------------------------------------------
        #50 // At time 601 - right after  !!! posedge clk !!!         
        begin
            // Expected values: clk = 1,    rst = 0,    btn = 1, 
            //                  out = 1,    state_test = 1 
            display_the_values( 6, 1, 0, 1, 1, 1, clk, rst, btn, 
                                out, state_test )                   ;
        end

        // ---------------------------------------------------------------
        #50 // At time 651
        // Button is false
        btn     =      0       ;

        // ---------------------------------------------------------------
        #50 // At time 700 - right after  !!! posedge clk !!!         
        begin
            // Expected values: clk = 1,    rst = 0,    btn = 0, 
            //                  out = 0,    state_test = 2 
            display_the_values( 7, 1, 0, 0, 0, 2, clk, rst, btn, 
                                out, state_test )                   ;
        end

        // ---------------------------------------------------------------
        #100 // At time 700 - right after  !!! posedge clk !!!         
        begin
            // Expected values: clk = 1,    rst = 0,    btn = 0, 
            //                  out = 0,    state_test = 0 
            display_the_values( 8, 1, 0, 0, 0, 0, clk, rst, btn, 
                                out, state_test )                   ;
        end
		  
		  #100
		  $finish;

    end
    
		  
endmodule

3.Valid_in/simulation/modelsim/dump.vcd
$date
	Fri Jan 15 15:07:08 2021
$end
$version
	ModelSim Version 10.5b
$end
$timescale
	1ps
$end

$scope module testbench $end
$var reg 1 ! clk $end
$var reg 1 " rst $end
$var reg 1 # btn $end
$var wire 1 $ out $end
$var wire 1 % state_test [1] $end
$var wire 1 & state_test [0] $end

$scope task display_the_values $end
$var reg 4 ' statement_number [3:0] $end
$var reg 1 ( clk_expected $end
$var reg 1 ) rst_expected $end
$var reg 16 * btn_expected [15:0] $end
$var reg 16 + out_expected [15:0] $end
$var reg 2 , state_test_expected [1:0] $end
$var reg 1 - clk_actual $end
$var reg 1 . rst_actual $end
$var reg 16 / btn_actual [15:0] $end
$var reg 16 0 out_actual [15:0] $end
$var reg 2 1 state_test_actual [1:0] $end
$upscope $end
$upscope $end
$enddefinitions $end
#0
$dumpvars
1!
1"
1#
bx '
x(
x)
bx *
bx +
bx ,
x-
x.
bx /
bx 0
bx 1
0$
0&
0%
$end
#50000
0!
#100000
1!
#101000
b1 '
1(
1)
b1 *
b0 +
b0 ,
1-
1.
b1 /
b0 0
b0 1
#150000
0!
#151000
0"
#200000
1!
1&
1$
#201000
b10 '
0)
b1 +
b1 ,
0.
b1 0
b1 1
#250000
0!
#300000
1!
0&
1%
0$
#301000
b11 '
b0 +
b10 ,
b0 0
b10 1
#350000
0!
#400000
1!
#401000
b100 '
#450000
0!
#451000
0#
#500000
1!
0%
#501000
b101 '
b0 *
b0 ,
b0 /
b0 1
#550000
0!
#551000
1#
#600000
1!
1&
1$
#601000
b110 '
b1 *
b1 +
b1 ,
b1 /
b1 0
b1 1
#650000
0!
#651000
0#
#700000
1!
0&
1%
0$
#701000
b111 '
b0 *
b0 +
b10 ,
b0 /
b0 0
b10 1
#750000
0!
#800000
1!
0%
#801000
b1000 '
b0 ,
b0 1
